fasttext/__init__.py
fasttext/fasttext.so
fasttext/model.py
fasttext-0.8.4.dist-info/METADATA
fasttext-0.8.4.dist-info/WHEEL
fasttext-0.8.4.dist-info/top_level.txt
fasttext-0.8.4.dist-info/RECORD
